valida/__init__.py
valida/callables.py
valida/casting.py
valida/conditions.py
valida/data.py
valida/datapath.py
valida/errors.py
valida/rules.py
valida/schema.py
valida/utils.py
valida-0.7.5.dist-info/LICENSE
valida-0.7.5.dist-info/METADATA
valida-0.7.5.dist-info/WHEEL
valida-0.7.5.dist-info/RECORD
