Metadata-Version: 2.1
Name: valida
Version: 0.7.5
Summary: Comprehensive validation library for nested data structures.
License: MIT
Author: Adam J. Plowman
Author-email: adam.plowman@manchester.ac.uk
Requires-Python: >=3.8,<4.0.0
Classifier: License :: OSI Approved :: MIT License
Classifier: Programming Language :: Python :: 3
Classifier: Programming Language :: Python :: 3.8
Classifier: Programming Language :: Python :: 3.9
Classifier: Programming Language :: Python :: 3.10
Classifier: Programming Language :: Python :: 3.11
Requires-Dist: ruamel.yaml (>=0.18.6,<0.19.0)
